pirrtools/__init__.py
pirrtools/cli.py
pirrtools/list_chunks.py
pirrtools/load.py
pirrtools/pandas.py
pirrtools/sequences.py
pirrtools/structures/__init__.py
pirrtools/structures/attrdict.py
pirrtools/structures/attrpath.py
pirrtools-0.2.20.dist-info/licenses/LICENSE
tests/__init__.py
tests/test_init.py
tests/test_list_chunks.py
tests/test_load.py
tests/test_pandas.py
tests/test_sequences.py
tests/test_structures.py
tests/test_to_rich.py
pirrtools-0.2.20.dist-info/METADATA
pirrtools-0.2.20.dist-info/WHEEL
pirrtools-0.2.20.dist-info/entry_points.txt
pirrtools-0.2.20.dist-info/top_level.txt
pirrtools-0.2.20.dist-info/RECORD
