Metadata-Version: 2.4
Name: pirrtools
Version: 0.2.20
Summary: Collection of tools I use in my projects
Author-email: Sean Smith <pirsquared.pirr@gmail.com>
License-Expression: MIT
Project-URL: Homepage, https://github.com/pirsquared/pirrtools
Classifier: Programming Language :: Python :: 3
Classifier: Operating System :: OS Independent
Requires-Python: >=3.9
License-File: LICENSE
Requires-Dist: pandas
Requires-Dist: numpy
Requires-Dist: feather-format
Requires-Dist: ipython
Requires-Dist: Pygments
Requires-Dist: rich
Requires-Dist: jinja2
Requires-Dist: matplotlib
Provides-Extra: dev
Requires-Dist: pytest>=8.0.0; extra == "dev"
Requires-Dist: pytest-cov>=5.0.0; extra == "dev"
Requires-Dist: pytest-xdist>=3.6.0; extra == "dev"
Requires-Dist: pytest-mock>=3.14.0; extra == "dev"
Requires-Dist: pytest-benchmark>=4.0.0; extra == "dev"
Requires-Dist: black>=24.0.0; extra == "dev"
Requires-Dist: isort>=5.13.0; extra == "dev"
Requires-Dist: ruff>=0.6.0; extra == "dev"
Requires-Dist: mypy>=1.11.0; extra == "dev"
Requires-Dist: pre-commit>=4.0.0; extra == "dev"
Requires-Dist: bandit>=1.7.0; extra == "dev"
Requires-Dist: types-requests; extra == "dev"
Requires-Dist: types-setuptools; extra == "dev"
Requires-Dist: pandas-stubs>=2.0.0; extra == "dev"
Requires-Dist: build>=1.2.0; extra == "dev"
Requires-Dist: twine>=5.1.0; extra == "dev"
Requires-Dist: wheel>=0.44.0; extra == "dev"
Requires-Dist: hatch>=1.12.0; extra == "dev"
Requires-Dist: tox>=4.21.0; extra == "dev"
Requires-Dist: coverage[toml]>=7.6.0; extra == "dev"
Requires-Dist: nox>=2024.4.15; extra == "dev"
Requires-Dist: rich-cli>=1.8.0; extra == "dev"
Requires-Dist: ipykernel>=6.29.0; extra == "dev"
Requires-Dist: notebook>=7.2.0; extra == "dev"
Provides-Extra: docs
Requires-Dist: sphinx>=8.0.0; extra == "docs"
Requires-Dist: sphinx-book-theme>=1.0.0; extra == "docs"
Requires-Dist: sphinx-autodoc-typehints>=2.0.0; extra == "docs"
Requires-Dist: sphinx-copybutton>=0.5.2; extra == "docs"
Requires-Dist: myst-parser>=3.0.0; extra == "docs"
Requires-Dist: sphinx-design>=0.6.0; extra == "docs"
Requires-Dist: nbsphinx>=0.9.0; extra == "docs"
Dynamic: license-file
